{
  "cardType": "ASSET",
  "companyName": "Healthcare REIT Sovereign",
  "industry": "REAL_ESTATE",
  "hybridIndustry": "MANUFACTURING",
  "placement": "UPSTREAM",
  "tier": 3,
  "baseValue": 22,
  "stress": 2,
  "income": 2,
  "baseLoanCapacity": 5,
  "loanCapacityIncreasePer10AssetValue": 5,
  "baseValueUpdateRule": {
    "outcomes": [
      { "range": [1, 1], "delta": -3 },
      { "range": [2, 3], "delta": -1 },
      { "range": [4, 5], "delta": 2 },
      { "range": [6, 6], "delta": 3 }
    ],
    "industryMechanic": "RE + MFG hybrid. Monk class (Actuary). STRESS-LINKED LOAN CAPACITY ×2 active. Peak Monk synergy at stress 0."
  },
  "verticalIntegrationRules": [
    {
      "requiresIndustry": "MANUFACTURING",
      "requiresPlacement": "MIDSTREAM",
      "effectType": "LOAN_CAPACITY_BONUS",
      "effectMagnitude": 2,
      "effectDescription": "If your current stress is ≤ 2: +2 loan cap on this asset (double the standard threshold bonus). If stress is 0: +4 loan cap. Actuary CEO's $5 longevity bonus stacks with maximum credit at stress 0 — peak Monk synergy."
    },
    {
      "requiresIndustry": "MANUFACTURING",
      "requiresPlacement": "DOWNSTREAM",
      "effectType": "SPECIAL",
      "effectDescription": "If you are alive at the final round, this asset's value counts as +3 for scoring."
    }
  ],
  "crossIndustrySynergies": [],
  "flavourText": "The longest-lived patients make the best landlords."
}
