{
  "cardType": "ASSET",
  "companyName": "Independent Studio",
  "industry": "MEDIA_ENTERTAINMENT",
  "placement": "UPSTREAM",
  "tier": 1,
  "baseValue": 5,
  "stress": 1,
  "income": 0,
  "baseLoanCapacity": 4,
  "loanCapacityIncreasePer10AssetValue": 4,
  "isBuzzDie": true,
  "baseValueUpdateRule": {
    "outcomes": [
      { "range": [1, 2], "delta": -1 },
      { "range": [3, 4], "delta": 1 },
      { "range": [5, 6], "delta": 3 }
    ],
    "industryMechanic": "Buzz die overrides GMI. Value determined by buzz die result, not standard GMI."
  },
  "verticalIntegrationRules": [
    {
      "requiresIndustry": "MEDIA_ENTERTAINMENT",
      "requiresPlacement": "MIDSTREAM",
      "effectType": "SPECIAL",
      "effectDescription": "When this asset rolls a good buzz result (3–6) this year, carry +1 to the buzz die on your next roll on any owned MEDIA asset this year (i.e. the threshold for good buzz on the next roll drops to 2–6). Does not stack across years. Buzz builds on buzz — but it's momentum, not control."
    }
  ],
  "crossIndustrySynergies": [],
  "flavourText": "Every blockbuster started as someone's side project."
}
